README.txt
setup.py
markovgen/__init__.py
markovgen/__main__.py
markovgen/markovgen.py
markovgen.egg-info/PKG-INFO
markovgen.egg-info/SOURCES.txt
markovgen.egg-info/dependency_links.txt
markovgen.egg-info/requires.txt
markovgen.egg-info/top_level.txt