Metadata-Version: 1.1
Name: markovgen
Version: 0.4.1
Summary: Another text generator based on Markov chains.
Home-page: https://github.com/ProgVal/markovgen
Author: Valentin Lorentz
Author-email: progval@progval.net
License: MIT
Platform: UNKNOWN
Classifier: Development Status :: 5 - Production/Stable
Classifier: Environment :: Console
Classifier: Intended Audience :: Developers
Classifier: License :: OSI Approved :: MIT License
Classifier: Operating System :: OS Independent
Classifier: Programming Language :: Python :: 3
Classifier: Programming Language :: Python :: 3.2
Classifier: Programming Language :: Python :: 3.3
Classifier: Programming Language :: Python :: 3.4
